nidn/__init__.py
nidn/fdtd/__init__.py
nidn/fdtd/backend.py
nidn/fdtd/boundaries.py
nidn/fdtd/constants.py
nidn/fdtd/conversions.py
nidn/fdtd/detectors.py
nidn/fdtd/fourier.py
nidn/fdtd/grid.py
nidn/fdtd/objects.py
nidn/fdtd/sources.py
nidn/fdtd/typing_.py
nidn/fdtd/visualization.py
nidn/fdtd/waveforms.py
nidn/fdtd_integration/__init__.py
nidn/fdtd_integration/calculate_transmission_reflection_coefficients.py
nidn/fdtd_integration/compute_fdtd_grid_scaling.py
nidn/fdtd_integration/compute_spectrum_fdtd.py
nidn/fdtd_integration/constants.py
nidn/fdtd_integration/init_fdtd.py
nidn/materials/__init__.py
nidn/materials/find_closest_material.py
nidn/materials/layer_builder.py
nidn/materials/material_collection.py
nidn/materials/data/aluminium_arsenide.csv
nidn/materials/data/aluminium_nitride.csv
nidn/materials/data/aluminium_oxide.csv
nidn/materials/data/gallium_arsenide.csv
nidn/materials/data/germanium.csv
nidn/materials/data/indium_arsenide.csv
nidn/materials/data/silicon_nitride.csv
nidn/materials/data/tantalum_pentoxide.csv
nidn/materials/data/titanium_oxide.csv
nidn/materials/data/zinc_oxide.csv
nidn/plots/__init__.py
nidn/plots/plot_eps_per_point.py
nidn/plots/plot_epsilon_grid.py
nidn/plots/plot_losses.py
nidn/plots/plot_material_grid.py
nidn/plots/plot_model_grid.py
nidn/plots/plot_model_grid_per_freq.py
nidn/plots/plot_spectra.py
nidn/plots/plot_spectrum.py
nidn/plots/save_all_plots.py
nidn/tests/__init__.py
nidn/tests/calculate_coefficient_test.py
nidn/tests/fdtd_test.py
nidn/tests/material_collection_test.py
nidn/tests/model_to_eps_grid_test.py
nidn/tests/target_frequency_test.py
nidn/tests/training_test.py
nidn/tests/trcwa_test.py
nidn/tests/validate_default_cfg_test.py
nidn/training/__init__.py
nidn/training/load_run.py
nidn/training/run_training.py
nidn/training/save_run.py
nidn/training/losses/likelihood_regularization_loss.py
nidn/training/losses/spectrum_loss.py
nidn/training/model/__init__.py
nidn/training/model/init_network.py
nidn-0.1.1.dist-info/LICENSE
nidn-0.1.1.dist-info/METADATA
nidn-0.1.1.dist-info/WHEEL
nidn-0.1.1.dist-info/top_level.txt
nidn-0.1.1.dist-info/RECORD
