Metadata-Version: 2.1
Name: nidn
Version: 0.1.1
Summary: A package for inverse material design of nanostructures using neural networks.
Home-page: https://github.com/esa/nidn
Author: ESA Advanced Concepts Team
Author-email: pablo.gomez@esa.int
License: UNKNOWN
Project-URL: Source, https://github.com/esa/nidn/
Platform: UNKNOWN
Classifier: Development Status :: 3 - Alpha
Classifier: Intended Audience :: Developers
Classifier: Intended Audience :: Science/Research
Classifier: Topic :: Scientific/Engineering :: Mathematics
Classifier: License :: OSI Approved :: GNU General Public License v3 (GPLv3)
Classifier: Programming Language :: Python :: 3.8
Requires-Python: >=3.8, <4
Requires-Dist: dotmap (>=1.3.24)
Requires-Dist: loguru (>=0.5.3)
Requires-Dist: matplotlib (>=3.3.3)
Requires-Dist: numpy (>=1.20.0)
Requires-Dist: pandas (>=1.3.1)
Requires-Dist: scipy (>=1.6.0)
Requires-Dist: tqdm (>=4.56.1)
Requires-Dist: toml (>=0.10.2)
Requires-Dist: torch (>=1.9)
